{
  "updated_at": "2026-07-07 11:47 北京时间",
  "source": "the-odds-api spreads",
  "count": 5,
  "handicap": {
    "argentina|egypt": {
      "home_team": "Argentina",
      "away_team": "Egypt",
      "home_point": -1.25,
      "away_point": 1.25,
      "book": "Pinnacle"
    },
    "switzerland|colombia": {
      "home_team": "Switzerland",
      "away_team": "Colombia",
      "home_point": 0.25,
      "away_point": -0.25,
      "book": "Pinnacle"
    },
    "france|morocco": {
      "home_team": "France",
      "away_team": "Morocco",
      "home_point": -1.0,
      "away_point": 1.0,
      "book": "Pinnacle"
    },
    "spain|belgium": {
      "home_team": "Spain",
      "away_team": "Belgium",
      "home_point": -0.75,
      "away_point": 0.75,
      "book": "Pinnacle"
    },
    "norway|england": {
      "home_team": "Norway",
      "away_team": "England",
      "home_point": 0.5,
      "away_point": -0.5,
      "book": "Pinnacle"
    }
  }
}